Metadata-Version: 2.1
Name: mangum-cli
Version: 0.0.1
Summary: CLI tools for Mangum
Home-page: https://github.com/erm/mangum-cli
Author: Jordan Eremieff
Author-email: jordan@eremieff.com
License: MIT
Platform: UNKNOWN
Classifier: License :: OSI Approved :: MIT License
Classifier: Operating System :: OS Independent
Classifier: Programming Language :: Python :: 3
Classifier: Programming Language :: Python :: 3.7
